bigraph_viz/__init__.py
bigraph_viz/convert_vivarium_v1.py
bigraph_viz/dict_utils.py
bigraph_viz/graph_from_file.py
bigraph_viz/visualize_types.py
bigraph_viz/methods/__init__.py
bigraph_viz/methods/generate_graph_dict.py
bigraph_viz-1.0.2.dist-info/licenses/AUTHORS.md
bigraph_viz-1.0.2.dist-info/licenses/LICENSE
bigraph_viz-1.0.2.dist-info/METADATA
bigraph_viz-1.0.2.dist-info/WHEEL
bigraph_viz-1.0.2.dist-info/top_level.txt
bigraph_viz-1.0.2.dist-info/RECORD
