Metadata-Version: 2.4
Name: bigraph-viz
Version: 1.0.2
Summary: A visualization method for displaying the structure of process bigraphs
Author-email: Eran Agmon <agmon.eran@gmail.com>
Maintainer-email: Eran Agmon <agmon.eran@gmail.com>
License:                                  Apache License
Keywords: visualization,systems biology,bigraph,graphviz,vivarium
Classifier: Development Status :: 3 - Alpha
Classifier: Intended Audience :: Science/Research
Classifier: License :: OSI Approved :: MIT License
Classifier: Operating System :: OS Independent
Classifier: Programming Language :: Python :: 3
Classifier: Programming Language :: Python :: 3 :: Only
Classifier: Programming Language :: Python :: 3.9
Classifier: Programming Language :: Python :: 3.10
Classifier: Programming Language :: Python :: 3.11
Classifier: Programming Language :: Python :: 3.12
Classifier: Topic :: Scientific/Engineering :: Visualization
Classifier: Topic :: Software Development :: Libraries
Requires-Python: >=3.11
License-File: LICENSE
License-File: AUTHORS.md
Requires-Dist: bigraph-schema
Requires-Dist: process-bigraph
Requires-Dist: graphviz
Dynamic: license-file
